<annotation>
	<folder />
	<filename>ppe_0668_jpg.rf.a9698369bed4930946fa5a453f60b2fe.jpg</filename>
	<path>ppe_0668_jpg.rf.a9698369bed4930946fa5a453f60b2fe.jpg</path>
	<source>
		<database>roboflow.ai</database>
	</source>
	<size>
		<width>256</width>
		<height>256</height>
		<depth>3</depth>
	</size>
	<segmented>0</segmented>
	<object>
		<name>helmet</name>
		<pose>Unspecified</pose>
		<truncated>0</truncated>
		<difficult>0</difficult>
		<occluded>0</occluded>
		<bndbox>
			<xmin>50</xmin>
			<xmax>93</xmax>
			<ymin>25</ymin>
			<ymax>76</ymax>
		</bndbox>
	</object>
	<object>
		<name>helmet</name>
		<pose>Unspecified</pose>
		<truncated>0</truncated>
		<difficult>0</difficult>
		<occluded>0</occluded>
		<bndbox>
			<xmin>163</xmin>
			<xmax>203</xmax>
			<ymin>32</ymin>
			<ymax>85</ymax>
		</bndbox>
	</object>
	<object>
		<name>person</name>
		<pose>Unspecified</pose>
		<truncated>0</truncated>
		<difficult>0</difficult>
		<occluded>0</occluded>
		<bndbox>
			<xmin>14</xmin>
			<xmax>93</xmax>
			<ymin>27</ymin>
			<ymax>255</ymax>
		</bndbox>
	</object>
	<object>
		<name>person</name>
		<pose>Unspecified</pose>
		<truncated>0</truncated>
		<difficult>0</difficult>
		<occluded>0</occluded>
		<bndbox>
			<xmin>161</xmin>
			<xmax>256</xmax>
			<ymin>33</ymin>
			<ymax>256</ymax>
		</bndbox>
	</object>
	<object>
		<name>vest</name>
		<pose>Unspecified</pose>
		<truncated>0</truncated>
		<difficult>0</difficult>
		<occluded>0</occluded>
		<bndbox>
			<xmin>189</xmin>
			<xmax>256</xmax>
			<ymin>86</ymin>
			<ymax>214</ymax>
		</bndbox>
	</object>
	<object>
		<name>vest</name>
		<pose>Unspecified</pose>
		<truncated>0</truncated>
		<difficult>0</difficult>
		<occluded>0</occluded>
		<bndbox>
			<xmin>18</xmin>
			<xmax>71</xmax>
			<ymin>87</ymin>
			<ymax>243</ymax>
		</bndbox>
	</object>
</annotation>