<annotation>
	<folder />
	<filename>ppe_0975_jpg.rf.6cb1e6078ffda5fe956ce411c711b501.jpg</filename>
	<path>ppe_0975_jpg.rf.6cb1e6078ffda5fe956ce411c711b501.jpg</path>
	<source>
		<database>roboflow.ai</database>
	</source>
	<size>
		<width>256</width>
		<height>256</height>
		<depth>3</depth>
	</size>
	<segmented>0</segmented>
	<object>
		<name>helmet</name>
		<pose>Unspecified</pose>
		<truncated>0</truncated>
		<difficult>0</difficult>
		<occluded>0</occluded>
		<bndbox>
			<xmin>72</xmin>
			<xmax>115</xmax>
			<ymin>43</ymin>
			<ymax>87</ymax>
		</bndbox>
	</object>
	<object>
		<name>helmet</name>
		<pose>Unspecified</pose>
		<truncated>0</truncated>
		<difficult>0</difficult>
		<occluded>0</occluded>
		<bndbox>
			<xmin>145</xmin>
			<xmax>188</xmax>
			<ymin>50</ymin>
			<ymax>95</ymax>
		</bndbox>
	</object>
	<object>
		<name>person</name>
		<pose>Unspecified</pose>
		<truncated>0</truncated>
		<difficult>0</difficult>
		<occluded>0</occluded>
		<bndbox>
			<xmin>50</xmin>
			<xmax>124</xmax>
			<ymin>40</ymin>
			<ymax>257</ymax>
		</bndbox>
	</object>
	<object>
		<name>person</name>
		<pose>Unspecified</pose>
		<truncated>0</truncated>
		<difficult>0</difficult>
		<occluded>0</occluded>
		<bndbox>
			<xmin>132</xmin>
			<xmax>220</xmax>
			<ymin>47</ymin>
			<ymax>257</ymax>
		</bndbox>
	</object>
</annotation>