<annotation>
	<folder />
	<filename>ppe_0955_jpg.rf.71692360648e949bf5fddf96f6e4890e.jpg</filename>
	<path>ppe_0955_jpg.rf.71692360648e949bf5fddf96f6e4890e.jpg</path>
	<source>
		<database>roboflow.ai</database>
	</source>
	<size>
		<width>256</width>
		<height>256</height>
		<depth>3</depth>
	</size>
	<segmented>0</segmented>
	<object>
		<name>person</name>
		<pose>Unspecified</pose>
		<truncated>0</truncated>
		<difficult>0</difficult>
		<occluded>0</occluded>
		<bndbox>
			<xmin>55</xmin>
			<xmax>93</xmax>
			<ymin>9</ymin>
			<ymax>146</ymax>
		</bndbox>
	</object>
	<object>
		<name>person</name>
		<pose>Unspecified</pose>
		<truncated>0</truncated>
		<difficult>0</difficult>
		<occluded>0</occluded>
		<bndbox>
			<xmin>190</xmin>
			<xmax>210</xmax>
			<ymin>53</ymin>
			<ymax>125</ymax>
		</bndbox>
	</object>
	<object>
		<name>person</name>
		<pose>Unspecified</pose>
		<truncated>0</truncated>
		<difficult>0</difficult>
		<occluded>0</occluded>
		<bndbox>
			<xmin>146</xmin>
			<xmax>163</xmax>
			<ymin>75</ymin>
			<ymax>127</ymax>
		</bndbox>
	</object>
	<object>
		<name>helmet</name>
		<pose>Unspecified</pose>
		<truncated>0</truncated>
		<difficult>0</difficult>
		<occluded>0</occluded>
		<bndbox>
			<xmin>76</xmin>
			<xmax>97</xmax>
			<ymin>12</ymin>
			<ymax>37</ymax>
		</bndbox>
	</object>
	<object>
		<name>person</name>
		<pose>Unspecified</pose>
		<truncated>0</truncated>
		<difficult>0</difficult>
		<occluded>0</occluded>
		<bndbox>
			<xmin>4</xmin>
			<xmax>27</xmax>
			<ymin>10</ymin>
			<ymax>77</ymax>
		</bndbox>
	</object>
</annotation>