<annotation>
	<folder />
	<filename>ppe_1127_jpg.rf.b62045e1850181e2e04d2bf61b1f4961.jpg</filename>
	<path>ppe_1127_jpg.rf.b62045e1850181e2e04d2bf61b1f4961.jpg</path>
	<source>
		<database>roboflow.ai</database>
	</source>
	<size>
		<width>256</width>
		<height>256</height>
		<depth>3</depth>
	</size>
	<segmented>0</segmented>
	<object>
		<name>helmet</name>
		<pose>Unspecified</pose>
		<truncated>0</truncated>
		<difficult>0</difficult>
		<occluded>0</occluded>
		<bndbox>
			<xmin>97</xmin>
			<xmax>113</xmax>
			<ymin>49</ymin>
			<ymax>62</ymax>
		</bndbox>
	</object>
	<object>
		<name>helmet</name>
		<pose>Unspecified</pose>
		<truncated>0</truncated>
		<difficult>0</difficult>
		<occluded>0</occluded>
		<bndbox>
			<xmin>180</xmin>
			<xmax>189</xmax>
			<ymin>57</ymin>
			<ymax>78</ymax>
		</bndbox>
	</object>
	<object>
		<name>vest</name>
		<pose>Unspecified</pose>
		<truncated>0</truncated>
		<difficult>0</difficult>
		<occluded>0</occluded>
		<bndbox>
			<xmin>206</xmin>
			<xmax>235</xmax>
			<ymin>68</ymin>
			<ymax>101</ymax>
		</bndbox>
	</object>
	<object>
		<name>vest</name>
		<pose>Unspecified</pose>
		<truncated>0</truncated>
		<difficult>0</difficult>
		<occluded>0</occluded>
		<bndbox>
			<xmin>83</xmin>
			<xmax>105</xmax>
			<ymin>74</ymin>
			<ymax>122</ymax>
		</bndbox>
	</object>
	<object>
		<name>person</name>
		<pose>Unspecified</pose>
		<truncated>0</truncated>
		<difficult>0</difficult>
		<occluded>0</occluded>
		<bndbox>
			<xmin>77</xmin>
			<xmax>115</xmax>
			<ymin>46</ymin>
			<ymax>195</ymax>
		</bndbox>
	</object>
	<object>
		<name>person</name>
		<pose>Unspecified</pose>
		<truncated>0</truncated>
		<difficult>0</difficult>
		<occluded>0</occluded>
		<bndbox>
			<xmin>178</xmin>
			<xmax>244</xmax>
			<ymin>59</ymin>
			<ymax>191</ymax>
		</bndbox>
	</object>
</annotation>